{
    "id": 90057148,
    "name": "Terminal Rampancy",
    "author": "Xyriak",
    "creators": [],
    "verifier": "BarGames",
    "verification": "https://www.youtube.com/watch?v=WbtHiBZF9oc&ab_channel=BarGames",
    "percentToQualify": 100,
    "song": "xKore - Splatterhouse (WIP)",
    "records": [
        {
            "user": "ByteLaw",
            "link": "https://youtu.be/T0VwjyFFoIo?si=0Ajd1m26jkdm_mGf",
            "percent": 100,
            "hz": 240,
            "mobile": false
        }
    ]
}
